undetected_chromedriver/__init__.py
undetected_chromedriver/_compat.py
undetected_chromedriver/cdp.py
undetected_chromedriver/devtool.py
undetected_chromedriver/dprocess.py
undetected_chromedriver/options.py
undetected_chromedriver/patcher.py
undetected_chromedriver/reactor.py
undetected_chromedriver/v2.py
undetected_chromedriver/webelement.py
undetected_chromedriver-3.1.6.dist-info/LICENSE
undetected_chromedriver-3.1.6.dist-info/METADATA
undetected_chromedriver-3.1.6.dist-info/WHEEL
undetected_chromedriver-3.1.6.dist-info/top_level.txt
undetected_chromedriver-3.1.6.dist-info/RECORD
