Metadata-Version: 2.1
Name: undetected-chromedriver
Version: 3.1.6
Summary: ('Selenium.webdriver.Chrome replacement with compatiblity for Brave, and other Chromium based browsers.', 'Not triggered by CloudFlare/Imperva/hCaptcha and such.', 'NOTE: results may vary due to many factors. No guarantees are given, except for ongoing efforts in understanding detection algorithms.')
Home-page: https://github.com/ultrafunkamsterdam/undetected-chromedriver
Author: UltrafunkAmsterdam
Author-email: info@blackhat-security.nl
License: GPL-3.0
Platform: UNKNOWN
Classifier: License :: OSI Approved :: GNU General Public License v3 (GPLv3)
Classifier: Programming Language :: Python :: 3
Classifier: Programming Language :: Python :: 3.7
Classifier: Programming Language :: Python :: 3.8
Classifier: Programming Language :: Python :: 3.9
Classifier: Programming Language :: Python :: 3.10
Classifier: Programming Language :: Python :: 3.11
License-File: LICENSE
